mqttactions/__init__.py
mqttactions/geo.py
mqttactions/inmemory_client.py
mqttactions/loader.py
mqttactions/payloadconversion.py
mqttactions/runtime.py
mqttactions/statemachine.py
mqttactions/cli/__init__.py
mqttactions/cli/discover.py
mqttactions/cli/run.py
mqttactions/cli/test.py
mqttactions/web/__init__.py
mqttactions/web/app.py
mqttactions/web/index.html
mqttactions/web/main.py
mqttactions/web/models.py
mqttactions/web/simulate.html
mqttactions/web/websocket.py
mqttactions-0.4.1.dist-info/METADATA
mqttactions-0.4.1.dist-info/WHEEL
mqttactions-0.4.1.dist-info/entry_points.txt
mqttactions-0.4.1.dist-info/licenses/LICENSE.txt
mqttactions-0.4.1.dist-info/RECORD
