Metadata-Version: 2.4
Name: mqttactions
Version: 0.4.1
Summary: Toolkit to interact with MQTT to build simple action rules
Project-URL: Homepage, https://github.com/mensi/mqttactions
Author-email: Manuel Stocker <mensi@mensi.ch>
License:                                  Apache License
License-File: LICENSE.txt
Requires-Python: >=3.10
Requires-Dist: click>=8.1.8
Requires-Dist: fastapi>=0.111.0
Requires-Dist: hatchling>=1.27.0
Requires-Dist: jinja2
Requires-Dist: paho-mqtt>=2.1.0
Requires-Dist: pydantic
Requires-Dist: suntime>=1.3.2
Requires-Dist: timezonefinder>=6.5.9
Requires-Dist: tzdata>=2025.2; sys_platform == 'win32'
Requires-Dist: uvicorn>=0.30.0
Requires-Dist: websockets
